{
  "file_path": "/Users/jim/Desktop/team-east-backtester/prosperity-uploader/generated/ashv2_ask_half_4_ask_mult_0.0_ask_mult_0.25_base_ske_0.25_bid_half_4.py",
  "file_hash": "1efaff48711efa2f3759cc81a240370427708a7076ed257d0056e5e790182713",
  "filename": "ashv2_ask_half_4_ask_mult_0.0_ask_mult_0.25_base_ske_0.25_bid_half_4.py",
  "status_code": 201,
  "response_body": {
    "success": true,
    "status": 201,
    "data": {
      "id": 183098,
      "teamId": "c6c2ea09-32b4-4658-9853-51b5364a6f52",
      "roundId": 2,
      "submittedAt": "2026-04-16T06:43:38.707Z",
      "submittedBy": {
        "firstName": "Albert",
        "lastName": "Ye"
      },
      "status": "SIMULATING",
      "filename": "109-ashv2_ask_half_4_ask_mult_0.0_ask_mult_0.25_base_ske_0.25_bid_half_4.py",
      "active": false,
      "simulationApplicationAlgoSubmissionIdentifier": "8cb54b8a-d46b-4347-ae1c-13f682e0ffb8"
    }
  },
  "timestamp": "2026-04-16T06:43:38.567878+00:00",
  "submission_id": "183098"
}