{
  "file_path": "/Users/jim/Desktop/team-east-backtester/prosperity-uploader/generated/ashv2_ask_half_1_ask_mult_0.0_bid_half_2_bid_mult_0.75_flatten__20.py",
  "file_hash": "61e9bb52dae546113000082ce454fdc9b423f77605358969db94def500b09de4",
  "filename": "ashv2_ask_half_1_ask_mult_0.0_bid_half_2_bid_mult_0.75_flatten__20.py",
  "status_code": 201,
  "response_body": {
    "success": true,
    "status": 201,
    "data": {
      "id": 186729,
      "teamId": "c6c2ea09-32b4-4658-9853-51b5364a6f52",
      "roundId": 2,
      "submittedAt": "2026-04-16T08:59:34.215Z",
      "submittedBy": {
        "firstName": "Albert",
        "lastName": "Ye"
      },
      "status": "SIMULATING",
      "filename": "176-ashv2_ask_half_1_ask_mult_0.0_bid_half_2_bid_mult_0.75_flatten__20.py",
      "active": false,
      "simulationApplicationAlgoSubmissionIdentifier": "411e22b2-053c-44c0-9223-b88c35c5cf12"
    }
  },
  "timestamp": "2026-04-16T08:59:33.934185+00:00",
  "submission_id": "186729"
}