{
  "file_path": "/Users/jim/Desktop/team-east-backtester/prosperity-uploader/generated/ashv2_ask_half_8_ask_mult_0.0_ask_mult_0.25_base_ske_0.5_bid_half_6.py",
  "file_hash": "1bbcfa745a06659be3d7c53fa912bd8296b757643460211e631233cda7af8e86",
  "filename": "ashv2_ask_half_8_ask_mult_0.0_ask_mult_0.25_base_ske_0.5_bid_half_6.py",
  "status_code": 201,
  "response_body": {
    "success": true,
    "status": 201,
    "data": {
      "id": 198704,
      "teamId": "c6c2ea09-32b4-4658-9853-51b5364a6f52",
      "roundId": 2,
      "submittedAt": "2026-04-16T14:36:38.493Z",
      "submittedBy": {
        "firstName": "Albert",
        "lastName": "Ye"
      },
      "status": "SIMULATING",
      "filename": "329-ashv2_ask_half_8_ask_mult_0.0_ask_mult_0.25_base_ske_0.5_bid_half_6.py",
      "active": false,
      "simulationApplicationAlgoSubmissionIdentifier": "2b7bf9a0-8553-445b-8bc8-d50fb21bd8a8"
    }
  },
  "timestamp": "2026-04-16T14:36:38.344942+00:00",
  "submission_id": "198704"
}